jxtr/__init__.py
jxtr/t.py
jxtr-2.1.5.dist-info/METADATA
jxtr-2.1.5.dist-info/WHEEL
jxtr-2.1.5.dist-info/top_level.txt
jxtr-2.1.5.dist-info/RECORD
