Metadata-Version: 2.1
Name: jxtr
Version: 2.1.5
Summary: Utilities, syllabic timestamp
Home-page: https://github.com/jxtrbtk/jxtr
Author: jxtrbtk
Author-email: jt.bontinck@gmail.com
